{
	"pages": [ //pages数组中第一项表示应用启动页，参考：https://uniapp.dcloud.io/collocation/pages
		{
			"path": "pages/views/Login",
			"style": {"navigationStyle":"custom"}
		},
		// 教练区域
		{
			"path": "pages/views/coachHome/coachHome",
			"style": {"navigationStyle":"custom"}
		},
		{
			"path": "pages/views/coachHome/myGrade/myGrade",
			"style": {
				"navigationBarTitleText": "我的排班",
				"navigationBarBackgroundColor":"#F8F8F8"
			}
		},
		{
			"path": "pages/views/coachHome/carMaintain/carMaintain",
			"style": {
				"navigationBarTitleText": "维修记录",
				"navigationBarBackgroundColor":"#F8F8F8",
				"enablePullDownRefresh":true//开启下拉刷新
			}
		},
		{
			"path": "pages/views/coachHome/carFuel/reful/reful",
			"style": {
				"navigationBarTitleText": "组件"
			}
		},
		{
			"path": "pages/views/coachHome/carFuel/carFuel",
			"style": {
				"navigationBarTitleText": "加油记录"
			}
		},
		{
			"path": "pages/views/coachHome/carMaintain/service/service",
			"style": {
				"navigationBarTitleText": "维修表单",
				"navigationBarBackgroundColor":"#F8F8F8"
			}
		},
		{
			"path": "pages/views/coachHome/examAudit/examAudit",
			"style": {
				"navigationBarTitleText": "代考审批",
				"navigationBarBackgroundColor":"#F8F8F8"
			}
		},
		// 校长区域的路由
		{
			"path": "pages/views/rectorHome/statistical/statistical",
			"style": {"navigationStyle":"custom"}
		},
		{
			"path": "pages/views/rectorHome/statistical/principalTable/principalTable",
			"style": {
				"navigationBarTitleText": "月招生统计",
				"navigationBarBackgroundColor":"#04BE9E",
				"navigationBarTextStyle":"white"
			}
		},
		{
			"path": "pages/views/rectorHome/statistical/incTable",
			"style": {
				"navigationBarTitleText": "收入统计",
				"navigationBarBackgroundColor":"#04BE9E",
				"navigationBarTextStyle":"white"
			}
		},{
			"path": "pages/views/rectorHome/statistical/quaTable",
			"style": {
				"navigationBarTitleText": "考试合格率统计表",
				"navigationBarBackgroundColor":"#04BE9E",
				"navigationBarTextStyle":"white"
			}
		},
		{
			"path": "pages/views/rectorHome/statistical/needTable",
			"style": {
				"navigationBarTitleText": "待考统计",
				"navigationBarBackgroundColor":"#04BE9E",
				"navigationBarTextStyle":"white"
			}
		},
		{
			"path": "pages/views/rectorHome/statistical/principalTable/detailsTable/detailsTable",
			"style": {
				"navigationBarTitleText": "详情统计",
				"navigationBarBackgroundColor":"#04BE9E",
				"navigationBarTextStyle":"white"
			}
		},
		{
			"path": "pages/views/rectorHome/statistical/referrer",
			"style": {
				"navigationBarTitleText": "推荐人统计",
				"navigationBarBackgroundColor":"#04BE9E",
				"navigationBarTextStyle":"white"
			}
		},
		{
			"path": "pages/views/rectorHome/rectorHome",
			"style": {
				"navigationBarTitleText": "数据快报",
				"navigationBarBackgroundColor":"#04BE9E",
				"navigationBarTextStyle":"white"
			}
		},
		{
			"path": "pages/views/rectorHome/statistical/refuelTable/refuelTable",
			"style": {
				"navigationBarTitleText": "加油统计",
				"navigationBarBackgroundColor":"#04BE9E",
				"navigationBarTextStyle":"white"
			}
		},
		{
			"path": "pages/views/rectorHome/statistical/refuelTable/fuelDetails/fuelDetails",
			"style": {
				"navigationBarTitleText": "燃料详情",
				"navigationBarBackgroundColor":"#04BE9E",
				"navigationBarTextStyle":"white"
			}
		},
		{
			"path": "pages/views/rectorHome/statistical/serviceTable",
			"style": {
				"navigationBarTitleText": "维修统计",
				"navigationBarBackgroundColor":"#04BE9E",
				"navigationBarTextStyle":"white"
			}
		},
		{
			"path": "pages/views/rectorHome/statistical/fuelAudit",
			"style": {
				"navigationBarTitleText": "燃料审核",
				"navigationBarBackgroundColor":"#04BE9E",
				"navigationBarTextStyle":"white"
			}
		},
		{
			"path": "pages/views/rectorHome/statistical/maintainAudit",
			"style": {
				"navigationBarTitleText": "维修记录",
				"navigationBarBackgroundColor":"#04BE9E",
				"navigationBarTextStyle":"white"
			}
		},
		{
			"path": "pages/views/rectorHome/statistical/examineEvaluate",
			"style": {
				"navigationBarTitleText": "查看评价",
				"navigationBarBackgroundColor":"#04BE9E",
				"navigationBarTextStyle":"white"
			}
		},
		{ // 学员模块
			"path": "pages/views/Home/Home",
			"style": {"navigationStyle":"custom"}
		},
		{
			"path": "pages/views/Home/record/record",
			"style": {
				"navigationBarTitleText": "培训日志",
				"navigationBarBackgroundColor":"#04BE9E",
				"navigationBarTextStyle":"white"
			}
		},
		{
			"path": "pages/views/Home/trainMake/trainMake",
			"style": {
				"navigationBarTitleText": "立刻预约",
				"navigationBarBackgroundColor":"#04BE9E",
				"navigationBarTextStyle":"white"
			}
		},
		{
			"path": "pages/views/Home/trainMake/Examination/Examination",
			"style": {
				"navigationBarTitleText": "可预约的教练",
				"navigationBarBackgroundColor":"#04BE9E",
				"navigationBarTextStyle":"white"
			}
		},
		{
			"path": "pages/views/Home/trainMake/againOrder/againOrder",
			"style": {
				"navigationBarTitleText": "//再次预约",
				"navigationBarBackgroundColor":"#04BE9E",
				"navigationBarTextStyle":"white"
			}
		},
		{
			"path": "pages/views/Home/trainMake/immeDiately/immeDiately",
			"style": {
				"navigationBarTitleText": "立刻评价",
				"navigationBarBackgroundColor":"#04BE9E",
				"navigationBarTextStyle":"white"
			}
		},
		{
			"path": "pages/views/Home/myEvaluate/myEvaluate",
			"style": {
				"navigationBarTitleText": "学员查看评价",
				"navigationBarBackgroundColor":"#04BE9E",
				"navigationBarTextStyle":"white"
			}
		}
	],
	"globalStyle": {
		"navigationBarTextStyle": "black",
		"navigationBarTitleText": "",
		"navigationBarBackgroundColor": "#FFFFFF",
		"backgroundColor": "#FFFFFF"
	}
}
